anywhere/__init__.py
anywhere/anywhere.proto
anywhere/base_types.py
anywhere/test_base_types.py
anywhere/protobuf3/__init__.py
anywhere/protobuf3/anywhere_pb2.py
anywhere/protobuf3/test_tools.py
anywhere/protobuf3/tools.py
anywhere/sqlalchemy/__init__.py
anywhere/sqlalchemy/field.py
anywhere/sqlalchemy/query_producer.py
anywhere/sqlalchemy/tests/__init__.py
anywhere/sqlalchemy/tests/conftest.py
anywhere/sqlalchemy/tests/test_query_producer.py
anywhere/sqlalchemy/tests/testset.py
anywhere/testsets/__init__.py
anywhere/testsets/reprs.py
anywhere/testsets/strings.py
anywhere/testsets/wheres.py
anywhere-0.2.5.dist-info/LICENSE
anywhere-0.2.5.dist-info/METADATA
anywhere-0.2.5.dist-info/WHEEL
anywhere-0.2.5.dist-info/top_level.txt
anywhere-0.2.5.dist-info/RECORD
